envtpl.py
envtpl-0.7.2.dist-info/METADATA
envtpl-0.7.2.dist-info/WHEEL
envtpl-0.7.2.dist-info/entry_points.txt
envtpl-0.7.2.dist-info/top_level.txt
envtpl-0.7.2.dist-info/RECORD
