Metadata-Version: 2.1
Name: envtpl
Version: 0.7.2
Summary: Render jinja2 templates on the command line using shell environment variables
Home-page: https://github.com/andreasjansson/envtpl
Author: Andreas Jansson
Author-email: andreas@jansson.me.uk
License: GPL v3
Keywords: template environment variables parameter substitution shell jinja2 docker
Classifier: Programming Language :: Python :: 3.7
Classifier: Programming Language :: Python :: 3.8
Classifier: Programming Language :: Python :: 3.9
Classifier: Programming Language :: Python :: 3.10
Classifier: License :: OSI Approved :: GNU General Public License v3 (GPLv3)
Requires-Python: >3.7
Requires-Dist: Jinja2 (~=3.0)
